hydra_plugins/hydra_ax_sweeper/__init__.py
hydra_plugins/hydra_ax_sweeper/_core.py
hydra_plugins/hydra_ax_sweeper/_earlystopper.py
hydra_plugins/hydra_ax_sweeper/ax_sweeper.py
hydra_plugins/hydra_ax_sweeper/config.py
hydra_ax_sweeper-1.2.0.dist-info/METADATA
hydra_ax_sweeper-1.2.0.dist-info/WHEEL
hydra_ax_sweeper-1.2.0.dist-info/top_level.txt
hydra_ax_sweeper-1.2.0.dist-info/RECORD
