Metadata-Version: 2.1
Name: hydra-ax-sweeper
Version: 1.2.0
Summary: Hydra Ax Sweeper plugin
Home-page: https://github.com/facebookresearch/hydra/
Author: Omry Yadan, Shagun Sodhani
Author-email: omry@fb.com, sshagunsodhani@gmail.com
License: UNKNOWN
Platform: UNKNOWN
Classifier: License :: OSI Approved :: MIT License
Classifier: Programming Language :: Python :: 3.7
Classifier: Programming Language :: Python :: 3.8
Classifier: Programming Language :: Python :: 3.9
Classifier: Programming Language :: Python :: 3.10
Classifier: Operating System :: POSIX :: Linux
Classifier: Operating System :: MacOS
Classifier: Development Status :: 4 - Beta
Requires-Dist: hydra-core (>=1.1.0.dev7)
Requires-Dist: ax-platform (<0.2.1,>=0.1.20)
Requires-Dist: torch
